PCSBFocus/__init__.py
PCSBFocus/focus.py
PCSBfocusPackage-0.0.1.dist-info/LICENSE
PCSBfocusPackage-0.0.1.dist-info/METADATA
PCSBfocusPackage-0.0.1.dist-info/WHEEL
PCSBfocusPackage-0.0.1.dist-info/top_level.txt
PCSBfocusPackage-0.0.1.dist-info/RECORD
